LICENSE
README.md
setup.py
mr_utilities/__init__.py
mr_utilities.egg-info/PKG-INFO
mr_utilities.egg-info/SOURCES.txt
mr_utilities.egg-info/dependency_links.txt
mr_utilities.egg-info/top_level.txt
mr_utilities/data/__init__.py
mr_utilities/data/color_pref_data.py
mr_utilities/data/experimental_data.py
mr_utilities/data/student_score_data.py
mr_utilities/data/temperature_data.py
mr_utilities/grades/__init__.py
mr_utilities/grades/generate_grade_data.py
mr_utilities/grades/generate_temperature_data.py
mr_utilities/grades/grade_utility.py