Metadata-Version: 2.1
Name: mr_utilities
Version: 0.3
Summary: Different utility functions for data processing
Home-page: https://git.ntnu.no/rouhani/utilities
Author: Majid Rouhani
Author-email: majid.rouhani@ntnu.no
Classifier: Programming Language :: Python :: 3
Classifier: License :: OSI Approved :: MIT License
Classifier: Operating System :: OS Independent
Requires-Python: >=3.6
License-File: LICENSE
